hello_playdatajuhankim-0.1.0.dist-info/METADATA
hello_playdatajuhankim-0.1.0.dist-info/WHEEL
hello_playdatajuhankim/__init__.py
hello_playdatajuhankim-0.1.0.dist-info/RECORD
