Metadata-Version: 2.1
Name: hello-playdataJuhanKim
Version: 0.1.0
Summary: The Python program
Author-Email: oneuse <joohan754@naver.com>
License: MIT
Requires-Python: >=3.8
